pyRFtk/.gitignore
pyRFtk/ConvertGeneral.py
pyRFtk/ReadDictData.py
pyRFtk/ReadTSF.py
pyRFtk/S_from_VI.py
pyRFtk/S_from_Y.py
pyRFtk/S_from_Z.py
pyRFtk/WriteTSF.py
pyRFtk/Y_from_S.py
pyRFtk/Z_from_S.py
pyRFtk/__init__.py
pyRFtk/_check_3D_shape_.py
pyRFtk/circuit.py
pyRFtk/codebase.py
pyRFtk/compareSs.py
pyRFtk/config.py
pyRFtk/findpath.py
pyRFtk/getlines.py
pyRFtk/maxfun.py
pyRFtk/plotVSWs.py
pyRFtk/printMatrices.py
pyRFtk/resolveTLparams.py
pyRFtk/rfArcObj.py
pyRFtk/rfBase.py
pyRFtk/rfCircuit.py
pyRFtk/rfCoupler.py
pyRFtk/rfGTL.py
pyRFtk/rfObject.py
pyRFtk/rfRLC.py
pyRFtk/rfTRL.py
pyRFtk/str_dict.py
pyRFtk/tictoc.py
pyRFtk/whoami.py
pyrftk-2.0.8.dist-info/METADATA
pyrftk-2.0.8.dist-info/WHEEL
pyrftk-2.0.8.dist-info/licenses/LICENCE
pyrftk-2.0.8.dist-info/RECORD
