Metadata-Version: 2.4
Name: pyRFtk
Version: 2.0.8
Summary: Design tool for RF antennae networks
Project-URL: Homepage, https://lpp-erm-kms.github.io/pyrftk/
Author-email: Frederic Durodie <frederic.durodie@rma.ac.be>, Arthur Adriaens <arthur.adriaens@mil.be>
License-File: LICENCE
Classifier: Operating System :: OS Independent
Classifier: Programming Language :: Python
Requires-Python: >=3.8
